setup.py
myadipkg_selva/__init__.py
myadipkg_selva/calculator.py
myadipkg_selva.egg-info/PKG-INFO
myadipkg_selva.egg-info/SOURCES.txt
myadipkg_selva.egg-info/dependency_links.txt
myadipkg_selva.egg-info/top_level.txt