Metadata-Version: 2.1
Name: myadipkg-selva
Version: 0.0.1
Summary: ADI Python Package module
Home-page: https://github.com/selvariyan-adi/mydemopkg
Author: selvariyan.natarajan
Author-email: selvariyan.natarajan@analog.com
Classifier: Programming Language :: Python :: 3
Classifier: Operating System :: OS Independent
